seq2label/__init__.py
seq2label/input.py
seq2label/input_paddle.py
seq2label/model.py
seq2label/model_paddle.py
seq2label/utils.py
seq2label/algorithms/__init__.py
seq2label/algorithms/text_cnn.py
seq2label/data/unicode_char_list.txt
seq2label/server/__init__.py
seq2label/server/http.py
seq2label/server/http_paddle.py
seq2label/server/paddle_inference.py
seq2label/trainer/__init__.py
seq2label/trainer/cli.py
seq2label/trainer/cli_paddle.py
seq2label/trainer/paddle_train.py
seq2label/trainer/train_model.py
seq2label/trainer/train_model_paddle.py
seq2label-0.0.2.dist-info/LICENSE
seq2label-0.0.2.dist-info/METADATA
seq2label-0.0.2.dist-info/WHEEL
seq2label-0.0.2.dist-info/top_level.txt
seq2label-0.0.2.dist-info/RECORD
